pcsget/__init__.py
pcsget/cmdline.py
pcsget/biz/__init__.py
pcsget/biz/config.py
pcsget/biz/log.py
pcsget/biz/login.py
pcsget/biz/sync.py
pcsget/biz/utils.py
pcs_get-0.9.23.dist-info/LICENSE
pcs_get-0.9.23.dist-info/METADATA
pcs_get-0.9.23.dist-info/WHEEL
pcs_get-0.9.23.dist-info/entry_points.txt
pcs_get-0.9.23.dist-info/top_level.txt
pcs_get-0.9.23.dist-info/RECORD
