Metadata-Version: 2.1
Name: pcs-get
Version: 0.9.23
Summary: the spider for pcs-protocol
Home-page: https://git.sysop.bigo.sg/zhoujianwei.garen/pcs-get
Author: zhoujianwei.garen
Author-email: zhoujianwei.garen@bigo.com
License: GPLv3+
Keywords: pcs,bigo,spider
Platform: all
Classifier: Environment :: Console
Classifier: License :: OSI Approved :: GNU General Public License v3 or later (GPLv3+)
Classifier: Natural Language :: Chinese (Simplified)
Classifier: Operating System :: OS Independent
Classifier: Programming Language :: Python
Classifier: Programming Language :: Python :: 3.8
License-File: LICENSE
Requires-Dist: requests
Requires-Dist: lxml
